salesforce_to_json/__init__.py
salesforce_to_json/__main__.py
sfmc_to_json/__init__.py
sfmc_to_json/formatter.py
sfmc_to_json-0.2.10.dist-info/METADATA
sfmc_to_json-0.2.10.dist-info/WHEEL
sfmc_to_json-0.2.10.dist-info/top_level.txt
sfmc_to_json-0.2.10.dist-info/RECORD
