Metadata-Version: 2.1
Name: sfmc-to-json
Version: 0.2.10
Summary: Used to format FuelSDK reponses into JSON
Home-page: https://github.com/emailrhoads/sfmc_response_to_json
License: MIT
Platform: UNKNOWN
Classifier: License :: OSI Approved :: MIT License
Classifier: Programming Language :: Python :: 2
Classifier: Programming Language :: Python :: 2.7
Requires-Dist: suds
